sentry_offline/__init__.py
sentry_offline/api.py
sentry_offline/py.typed
sentry_offline/storage.py
sentry_offline/transport.py
sentry_offline_transport-1.0.0.dist-info/LICENSE
sentry_offline_transport-1.0.0.dist-info/METADATA
sentry_offline_transport-1.0.0.dist-info/WHEEL
sentry_offline_transport-1.0.0.dist-info/RECORD
