Metadata-Version: 2.1
Name: sentry-offline-transport
Version: 1.0.0
Summary: Transport for Sentry that saves failed-to-send events on disk and resends them on the next launch.
License: MIT
Author: Roman Vlasenko
Author-email: klavionik@gmail.com
Requires-Python: >=3.8,<4.0
Classifier: License :: OSI Approved :: MIT License
Classifier: Programming Language :: Python :: 3
Classifier: Programming Language :: Python :: 3.8
Classifier: Programming Language :: Python :: 3.9
Classifier: Programming Language :: Python :: 3.10
Classifier: Programming Language :: Python :: 3.11
Classifier: Programming Language :: Python :: 3.12
Requires-Dist: sentry-sdk (>=2.0.0)
